fenics_ffc-2019.1.0.data/data/share/man/man1/ffc.1.gz
ffc/__init__.py
ffc/__main__.py
ffc/analysis.py
ffc/classname.py
ffc/codegeneration.py
ffc/compiler.py
ffc/fiatinterface.py
ffc/formatting.py
ffc/git_commit_hash.py
ffc/jitcompiler.py
ffc/log.py
ffc/main.py
ffc/optimization.py
ffc/parameters.py
ffc/plot.py
ffc/representation.py
ffc/representationutils.py
ffc/utils.py
ffc/wrappers.py
ffc/backends/__init__.py
ffc/backends/dolfin/__init__.py
ffc/backends/dolfin/capsules.py
ffc/backends/dolfin/form.py
ffc/backends/dolfin/functionspace.py
ffc/backends/dolfin/goalfunctional.py
ffc/backends/dolfin/includes.py
ffc/backends/dolfin/wrappers.py
ffc/backends/ufc/__init__.py
ffc/backends/ufc/coordinate_mapping.py
ffc/backends/ufc/dofmap.py
ffc/backends/ufc/finite_element.py
ffc/backends/ufc/form.py
ffc/backends/ufc/function.py
ffc/backends/ufc/integrals.py
ffc/backends/ufc/ufc.h
ffc/backends/ufc/ufc_geometry.h
ffc/errorcontrol/__init__.py
ffc/errorcontrol/errorcontrol.py
ffc/errorcontrol/errorcontrolgenerators.py
ffc/quadrature/__init__.py
ffc/quadrature/codesnippets.py
ffc/quadrature/cpp.py
ffc/quadrature/deprecation.py
ffc/quadrature/expr.py
ffc/quadrature/floatvalue.py
ffc/quadrature/fraction.py
ffc/quadrature/optimisedquadraturetransformer.py
ffc/quadrature/parameters.py
ffc/quadrature/product.py
ffc/quadrature/quadraturegenerator.py
ffc/quadrature/quadratureoptimization.py
ffc/quadrature/quadraturerepresentation.py
ffc/quadrature/quadraturetransformer.py
ffc/quadrature/quadraturetransformerbase.py
ffc/quadrature/quadratureutils.py
ffc/quadrature/reduce_operations.py
ffc/quadrature/sumobj.py
ffc/quadrature/symbol.py
ffc/quadrature/symbolics.py
ffc/quadrature/tabulate_basis.py
ffc/tsfc/__init__.py
ffc/tsfc/tsfcgenerator.py
ffc/tsfc/tsfcoptimization.py
ffc/tsfc/tsfcrepresentation.py
ffc/uflacs/__init__.py
ffc/uflacs/build_uflacs_ir.py
ffc/uflacs/elementtables.py
ffc/uflacs/integralgenerator.py
ffc/uflacs/params.py
ffc/uflacs/tools.py
ffc/uflacs/uflacsgenerator.py
fenics_ffc-2019.1.0.dist-info/AUTHORS
fenics_ffc-2019.1.0.dist-info/COPYING
fenics_ffc-2019.1.0.dist-info/COPYING.LESSER
fenics_ffc-2019.1.0.dist-info/LICENSE
fenics_ffc-2019.1.0.dist-info/METADATA
fenics_ffc-2019.1.0.dist-info/WHEEL
fenics_ffc-2019.1.0.dist-info/entry_points.txt
fenics_ffc-2019.1.0.dist-info/top_level.txt
fenics_ffc-2019.1.0.dist-info/RECORD
