Metadata-Version: 2.1
Name: fenics-ffc
Version: 2019.1.0
Summary: The FEniCS Form Compiler
Home-page: https://bitbucket.org/fenics-project/ffc/
Author: Anders Logg, Kristian Oelgaard, Marie Rognes, Garth N. Wells,
Requires-Dist: numpy
Requires-Dist: fenics-fiat (<2019.2,>=2019.1.0)
Requires-Dist: fenics-ufl (<2019.2,>=2019.1.0)
Requires-Dist: fenics-dijitso (<2019.2,>=2019.1.0)
